universa/__init__.py
universa/exceptions.py
universa/transport.py
universa/utils.py
universa/tests/__init__.py
universa/tests/test_contract.py
universa/tests/test_crypto.py
universa/tests/test_hash.py
universa/tests/test_transport.py
universa/types/__init__.py
universa/types/base.py
universa/types/binder.py
universa/types/contract.py
universa/types/crypto.py
universa/types/hash_id.py
universa/types/network.py
universa/types/permissions.py
universa/types/roles.py
universa/types/utils.py
universa-0.2.0.dist-info/LICENSE
universa-0.2.0.dist-info/METADATA
universa-0.2.0.dist-info/WHEEL
universa-0.2.0.dist-info/top_level.txt
universa-0.2.0.dist-info/RECORD
